<?xml version="1.0" encoding="utf-8" ?>
<dwsync>
<file name="adminattributes.php" server="ftp.lifestones.biz//" local="131855003496211131" remote="131837050800000000" Dst="2" />
<file name="attachments.php" server="ftp.lifestones.biz//" local="131855003498120393" remote="131837050800000000" Dst="2" />
<file name="attributes.php" server="ftp.lifestones.biz//" local="131855003503598776" remote="131837050800000000" Dst="2" />
<file name="bounces.php" server="ftp.lifestones.biz//" local="131855003504908356" remote="131837050800000000" Dst="2" />
<file name="community.php" server="ftp.lifestones.biz//" local="131855003506767644" remote="131837050800000000" Dst="2" />
<file name="configure.php" server="ftp.lifestones.biz//" local="131855003512289256" remote="131837050800000000" Dst="2" />
<file name="defaults.php" server="ftp.lifestones.biz//" local="131855003514168674" remote="131837050800000000" Dst="2" />
<file name="embargo.php" server="ftp.lifestones.biz//" local="131855003515983016" remote="131837050800000000" Dst="2" />
<file name="eventlog.php" server="ftp.lifestones.biz//" local="131855003519678828" remote="131837050800000000" Dst="2" />
<file name="format.php" server="ftp.lifestones.biz//" local="131855003523405454" remote="131837050800000000" Dst="2" />
<file name="export.php" server="ftp.lifestones.biz//" local="131855003523425550" remote="131837050800000000" Dst="2" />
<file name="from.php" server="ftp.lifestones.biz//" local="131855003527094213" remote="131837050800000000" Dst="2" />
<file name="getrss.php" server="ftp.lifestones.biz//" local="131855003530803174" remote="131837050800000000" Dst="2" />
<file name="import.php" server="ftp.lifestones.biz//" local="131855003531042970" remote="131837050800000000" Dst="2" />
<file name="import1.php" server="ftp.lifestones.biz//" local="131855003534511857" remote="131837050800000000" Dst="2" />
<file name="import2.php" server="ftp.lifestones.biz//" local="131855003538169238" remote="131837050800000000" Dst="2" />
<file name="importadmin.php" server="ftp.lifestones.biz//" local="131855003540161003" remote="131837050800000000" Dst="2" />
<file name="login.php" server="ftp.lifestones.biz//" local="131855003542015616" remote="131837050800000000" Dst="2" />
<file name="logout.php" server="ftp.lifestones.biz//" local="131855003545678349" remote="131837050800000000" Dst="2" />
<file name="members.php" server="ftp.lifestones.biz//" local="131855003547687724" remote="131837050800000000" Dst="2" />
<file name="mergeattributes.php" server="ftp.lifestones.biz//" local="131855003549507237" remote="131837050800000000" Dst="2" />
<file name="message.php" server="ftp.lifestones.biz//" local="131855003553219077" remote="131837050800000000" Dst="2" />
<file name="messages.php" server="ftp.lifestones.biz//" local="131855003556900630" remote="131837050800000000" Dst="2" />
<file name="reconcileusers.php" server="ftp.lifestones.biz//" local="131855003556920502" remote="131837050800000000" Dst="2" />
<file name="send.php" server="ftp.lifestones.biz//" local="131855003560723089" remote="131837050800000000" Dst="2" />
<file name="setup.php" server="ftp.lifestones.biz//" local="131855003564308031" remote="131837050800000000" Dst="2" />
<file name="spage.php" server="ftp.lifestones.biz//" local="131855003564497982" remote="131837050800000000" Dst="2" />
<file name="spageedit.php" server="ftp.lifestones.biz//" local="131855003568121014" remote="131837050800000000" Dst="2" />
<file name="templates.php" server="ftp.lifestones.biz//" local="131855003571835799" remote="131837050800000000" Dst="2" />
<file name="usermgt.php" server="ftp.lifestones.biz//" local="131855003571995738" remote="131837050800000000" Dst="2" />
<file name="vote.php" server="ftp.lifestones.biz//" local="131855003575554603" remote="131837050800000000" Dst="2" />
<file name="adminattributes.php" server="ftp.lifestones.co.nz" local="131935254349438235" remote="131863831200000000" Dst="2" />
<file name="attachments.php" server="ftp.lifestones.co.nz" local="131935254352546453" remote="131863831200000000" Dst="2" />
<file name="attributes.php" server="ftp.lifestones.co.nz" local="131935254352846292" remote="131863831200000000" Dst="2" />
<file name="bounces.php" server="ftp.lifestones.co.nz" local="131935254356555374" remote="131863831200000000" Dst="2" />
<file name="community.php" server="ftp.lifestones.co.nz" local="131935254359665920" remote="131863831200000000" Dst="2" />
<file name="configure.php" server="ftp.lifestones.co.nz" local="131935254359955757" remote="131863831200000000" Dst="2" />
<file name="defaults.php" server="ftp.lifestones.co.nz" local="131935254363691437" remote="131863831200000000" Dst="2" />
<file name="embargo.php" server="ftp.lifestones.co.nz" local="131935254366759672" remote="131863831200000000" Dst="2" />
<file name="eventlog.php" server="ftp.lifestones.co.nz" local="131935254367099488" remote="131863831200000000" Dst="2" />
<file name="export.php" server="ftp.lifestones.co.nz" local="131935254371736827" remote="131863831200000000" Dst="2" />
<file name="format.php" server="ftp.lifestones.co.nz" local="131935254374128320" remote="131863831200000000" Dst="2" />
<file name="from.php" server="ftp.lifestones.co.nz" local="131935254374328136" remote="131863831200000000" Dst="2" />
<file name="getrss.php" server="ftp.lifestones.co.nz" local="131935254379245480" remote="131863831200000000" Dst="2" />
<file name="import.php" server="ftp.lifestones.co.nz" local="131935254381174195" remote="131863831200000000" Dst="2" />
<file name="import1.php" server="ftp.lifestones.co.nz" local="131935254382633353" remote="131863831200000000" Dst="2" />
<file name="import2.php" server="ftp.lifestones.co.nz" local="131935254386721005" remote="131863831200000000" Dst="2" />
<file name="importadmin.php" server="ftp.lifestones.co.nz" local="131935254389459432" remote="131863831200000000" Dst="2" />
<file name="login.php" server="ftp.lifestones.co.nz" local="131935254389649326" remote="131863831200000000" Dst="2" />
<file name="logout.php" server="ftp.lifestones.co.nz" local="131935254394576511" remote="131863831200000000" Dst="2" />
<file name="members.php" server="ftp.lifestones.co.nz" local="131935254396465427" remote="131863831200000000" Dst="2" />
<file name="mergeattributes.php" server="ftp.lifestones.co.nz" local="131935254397994560" remote="131863831200000000" Dst="2" />
<file name="message.php" server="ftp.lifestones.co.nz" local="131935254401422568" remote="131863831200000000" Dst="2" />
<file name="messages.php" server="ftp.lifestones.co.nz" local="131935254404810622" remote="131863831200000000" Dst="2" />
<file name="reconcileusers.php" server="ftp.lifestones.co.nz" local="131935254404830615" remote="131863831200000000" Dst="2" />
<file name="send.php" server="ftp.lifestones.co.nz" local="131935254408588456" remote="131863831200000000" Dst="2" />
<file name="setup.php" server="ftp.lifestones.co.nz" local="131935254411716667" remote="131863831200000000" Dst="2" />
<file name="spage.php" server="ftp.lifestones.co.nz" local="131935254411996670" remote="131863831200000000" Dst="2" />
<file name="spageedit.php" server="ftp.lifestones.co.nz" local="131935254415724359" remote="131863831200000000" Dst="2" />
<file name="templates.php" server="ftp.lifestones.co.nz" local="131935254418802593" remote="131863831200000000" Dst="2" />
<file name="usermgt.php" server="ftp.lifestones.co.nz" local="131935254419142408" remote="131863831200000000" Dst="2" />
<file name="vote.php" server="ftp.lifestones.co.nz" local="131935254422580426" remote="131863831200000000" Dst="2" />
</dwsync>